ci_exec/__init__.py
ci_exec/colorize.py
ci_exec/core.py
ci_exec/patch.py
ci_exec/provider.py
ci_exec/py.typed
ci_exec/utils.py
ci_exec/parsers/__init__.py
ci_exec/parsers/cmake_parser.py
ci_exec/parsers/utils.py
ci_exec-0.1.2.dist-info/LICENSE
ci_exec-0.1.2.dist-info/METADATA
ci_exec-0.1.2.dist-info/WHEEL
ci_exec-0.1.2.dist-info/top_level.txt
ci_exec-0.1.2.dist-info/RECORD
