Metadata-Version: 2.1
Name: ci-exec
Version: 0.1.2
Summary: A wrapper package designed for running continuous integration (CI) build steps using Python 3.6+.
Home-page: https://github.com/svenevs/ci_exec
Author: Stephen McDowell
Author-email: svenevs.pypi@gmail.com
License: Apache v2.0
Project-URL: Documentation, https://ci-exec.readthedocs.io/en/latest/
Project-URL: Source, https://github.com/svenevs/ci_exec
Project-URL: Tracker, https://github.com/svenevs/ci_exec/issues
Platform: UNKNOWN
Classifier: Development Status :: 3 - Alpha
Classifier: Intended Audience :: Developers
Classifier: Topic :: Software Development :: Build Tools
Classifier: License :: OSI Approved :: Apache Software License
Classifier: Programming Language :: Python :: 3.6
Classifier: Programming Language :: Python :: 3.7
Classifier: Programming Language :: Python :: 3.8
Classifier: Programming Language :: Python :: 3.9
License-File: LICENSE
